Metadata-Version: 2.1
Name: django-graphviz-templates
Version: 0.1.0
Summary: a quick render for django from graphviz formatted file
Home-page: https://github.com/axplus/django_graphviz_templates
Author: yijie zeng
Author-email: axplus@163.com
License: UNKNOWN
Platform: UNKNOWN
Classifier: Programming Language :: Python :: 2
Classifier: License :: OSI Approved :: MIT License
Classifier: Operating System :: OS Independent
Requires-Python: >=2.6
